odoo/addons/event_sale_session/README.rst
odoo/addons/event_sale_session/__init__.py
odoo/addons/event_sale_session/__manifest__.py
odoo/addons/event_sale_session/demo/event_session.xml
odoo/addons/event_sale_session/i18n/es.po
odoo/addons/event_sale_session/i18n/event_sale_session.pot
odoo/addons/event_sale_session/i18n/fr.po
odoo/addons/event_sale_session/i18n/it.po
odoo/addons/event_sale_session/models/__init__.py
odoo/addons/event_sale_session/models/event_registration.py
odoo/addons/event_sale_session/models/event_session.py
odoo/addons/event_sale_session/models/sale_order_line.py
odoo/addons/event_sale_session/readme/CONTRIBUTORS.md
odoo/addons/event_sale_session/readme/DESCRIPTION.md
odoo/addons/event_sale_session/readme/USAGE.md
odoo/addons/event_sale_session/reports/__init__.py
odoo/addons/event_sale_session/reports/event_sale_report.py
odoo/addons/event_sale_session/reports/event_sale_report.xml
odoo/addons/event_sale_session/reports/sale_report.py
odoo/addons/event_sale_session/reports/sale_report.xml
odoo/addons/event_sale_session/static/description/icon.png
odoo/addons/event_sale_session/static/description/index.html
odoo/addons/event_sale_session/static/src/js/EventConfiguratorController.esm.js
odoo/addons/event_sale_session/tests/__init__.py
odoo/addons/event_sale_session/tests/test_event_sale_session.py
odoo/addons/event_sale_session/views/event_session.xml
odoo/addons/event_sale_session/views/sale_order.xml
odoo/addons/event_sale_session/wizard/__init__.py
odoo/addons/event_sale_session/wizard/event_configurator.py
odoo/addons/event_sale_session/wizard/event_configurator.xml
odoo/addons/event_sale_session/wizard/event_edit_registration.py
odoo/addons/event_sale_session/wizard/event_edit_registration.xml
odoo_addon_event_sale_session-18.0.1.0.0.2.dist-info/METADATA
odoo_addon_event_sale_session-18.0.1.0.0.2.dist-info/WHEEL
odoo_addon_event_sale_session-18.0.1.0.0.2.dist-info/top_level.txt
odoo_addon_event_sale_session-18.0.1.0.0.2.dist-info/RECORD
